[
    {
      "start_date": "2016-10-10 0:00:00",
      "end_date": "2016-10-10 23:59:59",
      "asrc": 200772,
      "asra": 200771
    },
    {
      "start_date": "2016-10-11 0:00:00",
      "end_date": "2016-10-11 23:59:59",
      "asrc": 200774,
      "asra": 200773
    },
    {
      "start_date": "2016-10-12 0:00:00",
      "end_date": "2016-10-12 23:59:59",
      "asrc": 200776,
      "asra": 200775
    },
    {
      "start_date": "2016-10-13 0:00:00",
      "end_date": "2016-10-13 23:59:59",
      "asrc": 200778,
      "asra": 200777
    },
    {
      "start_date": "2016-10-14 0:00:00",
      "end_date": "2016-10-14 23:59:59",
      "asrc": 200780,
      "asra": 200779
    },
    {
      "start_date": "2016-10-15 0:00:00",
      "end_date": "2016-10-15 23:59:59",
      "asrc": 200782,
      "asra": 200781
    },
    {
      "start_date": "2016-10-16 0:00:00",
      "end_date": "2016-10-16 23:59:59",
      "asrc": 200784,
      "asra": 200783
    },
    {
      "start_date": "2016-10-17 0:00:00",
      "end_date": "2016-10-17 23:59:59",
      "asrc": 200786,
      "asra": 200785
    },
    {
      "start_date": "2016-10-18 0:00:00",
      "end_date": "2016-10-18 23:59:59",
      "asrc": 200788,
      "asra": 200787
    },
    {
      "start_date": "2016-10-19 0:00:00",
      "end_date": "2016-10-19 23:59:59",
      "asrc": 200790,
      "asra": 200789
    },
    {
      "start_date": "2016-10-20 0:00:00",
      "end_date": "2016-10-20 23:59:59",
      "asrc": 200792,
      "asra": 200791
    },
    {
      "start_date": "2016-10-21 0:00:00",
      "end_date": "2016-10-21 23:59:59",
      "asrc": 200794,
      "asra": 200793
    },
    {
      "start_date": "2016-10-22 0:00:00",
      "end_date": "2016-10-22 23:59:59",
      "asrc": 200796,
      "asra": 200795
    },
    {
      "start_date": "2016-10-23 0:00:00",
      "end_date": "2016-10-23 23:59:59",
      "asrc": 200798,
      "asra": 200797
    },
    {
      "start_date": "2016-10-24 0:00:00",
      "end_date": "2016-10-24 23:59:59",
      "asrc": 200800,
      "asra": 200799
    },
    {
      "start_date": "2016-10-25 0:00:00",
      "end_date": "2016-10-25 23:59:59",
      "asrc": 200802,
      "asra": 200801
    },
    {
      "start_date": "2016-10-26 0:00:00",
      "end_date": "2016-10-26 23:59:59",
      "asrc": 200804,
      "asra": 200803
    },
    {
      "start_date": "2016-10-27 0:00:00",
      "end_date": "2016-10-27 23:59:59",
      "asrc": 200806,
      "asra": 200805
    },
    {
      "start_date": "2016-10-28 0:00:00",
      "end_date": "2016-10-28 23:59:59",
      "asrc": 200808,
      "asra": 200807
    },
    {
      "start_date": "2016-10-29 0:00:00",
      "end_date": "2016-10-29 23:59:59",
      "asrc": 200810,
      "asra": 200809
    },
    {
      "start_date": "2016-10-30 0:00:00",
      "end_date": "2016-10-30 23:59:59",
      "asrc": 200812,
      "asra": 200811
    },
    {
      "start_date": "2016-10-31 0:00:00",
      "end_date": "2016-10-31 23:59:59",
      "asrc": 200814,
      "asra": 200813
    },
    {
      "start_date": "2016-11-01 0:00:00",
      "end_date": "2016-11-01 23:59:59",
      "asrc": 200816,
      "asra": 200815
    },
    {
      "start_date": "2016-11-02 0:00:00",
      "end_date": "2016-11-02 23:59:59",
      "asrc": 200818,
      "asra": 200817
    },
    {
      "start_date": "2016-11-03 0:00:00",
      "end_date": "2016-11-03 23:59:59",
      "asrc": 200820,
      "asra": 200819
    },
    {
      "start_date": "2016-11-04 0:00:00",
      "end_date": "2016-11-04 23:59:59",
      "asrc": 200822,
      "asra": 200821
    },
    {
      "start_date": "2016-11-05 0:00:00",
      "end_date": "2016-11-05 23:59:59",
      "asrc": 200824,
      "asra": 200823
    },
    {
      "start_date": "2016-11-06 0:00:00",
      "end_date": "2016-11-06 23:59:59",
      "asrc": 200826,
      "asra": 200825
    },
    {
      "start_date": "2016-11-07 0:00:00",
      "end_date": "2016-11-07 23:59:59",
      "asrc": 200828,
      "asra": 200827
    },
    {
      "start_date": "2016-11-08 0:00:00",
      "end_date": "2016-11-08 23:59:59",
      "asrc": 200830,
      "asra": 200829
    },
    {
      "start_date": "2016-11-09 0:00:00",
      "end_date": "2016-11-09 23:59:59",
      "asrc": 200832,
      "asra": 200831
    },
    {
      "start_date": "2016-11-10 0:00:00",
      "end_date": "2016-11-10 23:59:59",
      "asrc": 200834,
      "asra": 200833
    },
    {
      "start_date": "2016-11-11 0:00:00",
      "end_date": "2016-11-11 23:59:59",
      "asrc": 200836,
      "asra": 200835
    },
    {
      "start_date": "2016-11-12 0:00:00",
      "end_date": "2016-11-12 23:59:59",
      "asrc": 200838,
      "asra": 200837
    },
    {
      "start_date": "2016-11-13 0:00:00",
      "end_date": "2016-11-13 23:59:59",
      "asrc": 200840,
      "asra": 200839
    },
    {
      "start_date": "2016-11-14 0:00:00",
      "end_date": "2016-11-14 23:59:59",
      "asrc": 200842,
      "asra": 200841
    },
    {
      "start_date": "2016-11-15 0:00:00",
      "end_date": "2016-11-15 23:59:59",
      "asrc": 200844,
      "asra": 200843
    },
    {
      "start_date": "2016-11-16 0:00:00",
      "end_date": "2016-11-16 23:59:59",
      "asrc": 200846,
      "asra": 200845
    },
    {
      "start_date": "2016-11-17 0:00:00",
      "end_date": "2016-11-17 23:59:59",
      "asrc": 200848,
      "asra": 200847
    },
    {
      "start_date": "2016-11-18 0:00:00",
      "end_date": "2016-11-18 23:59:59",
      "asrc": 200850,
      "asra": 200849
    },
    {
      "start_date": "2016-11-19 0:00:00",
      "end_date": "2016-11-19 23:59:59",
      "asrc": 200852,
      "asra": 200851
    },
    {
      "start_date": "2016-11-20 0:00:00",
      "end_date": "2016-11-20 23:59:59",
      "asrc": 200854,
      "asra": 200853
    }
  ]